LICENSE
MANIFEST.in
README.md
setup.py
test/test_forward.py
test/test_grad.py
test/__pycache__/test_forward.cpython-36-pytest-5.3.1.pyc
test/__pycache__/test_grad.cpython-36-pytest-5.3.1.pyc
torch_dwconv/__init__.py
torch_dwconv/dwconv.cpp
torch_dwconv/dwconv.py
torch_dwconv/dwconv_kernel.cu
torch_dwconv.egg-info/PKG-INFO
torch_dwconv.egg-info/SOURCES.txt
torch_dwconv.egg-info/dependency_links.txt
torch_dwconv.egg-info/top_level.txt
torch_dwconv/__pycache__/__init__.cpython-36.pyc
torch_dwconv/__pycache__/dwconv.cpython-36.pyc
torch_dwconv/cub/cub.cuh
torch_dwconv/cub/util_allocator.cuh
torch_dwconv/cub/util_arch.cuh
torch_dwconv/cub/util_debug.cuh
torch_dwconv/cub/util_device.cuh
torch_dwconv/cub/util_macro.cuh
torch_dwconv/cub/util_namespace.cuh
torch_dwconv/cub/util_ptx.cuh
torch_dwconv/cub/util_type.cuh
torch_dwconv/cub/agent/agent_histogram.cuh
torch_dwconv/cub/agent/agent_radix_sort_downsweep.cuh
torch_dwconv/cub/agent/agent_radix_sort_upsweep.cuh
torch_dwconv/cub/agent/agent_reduce.cuh
torch_dwconv/cub/agent/agent_reduce_by_key.cuh
torch_dwconv/cub/agent/agent_rle.cuh
torch_dwconv/cub/agent/agent_scan.cuh
torch_dwconv/cub/agent/agent_segment_fixup.cuh
torch_dwconv/cub/agent/agent_select_if.cuh
torch_dwconv/cub/agent/agent_spmv_orig.cuh
torch_dwconv/cub/agent/single_pass_scan_operators.cuh
torch_dwconv/cub/block/block_adjacent_difference.cuh
torch_dwconv/cub/block/block_discontinuity.cuh
torch_dwconv/cub/block/block_exchange.cuh
torch_dwconv/cub/block/block_histogram.cuh
torch_dwconv/cub/block/block_load.cuh
torch_dwconv/cub/block/block_radix_rank.cuh
torch_dwconv/cub/block/block_radix_sort.cuh
torch_dwconv/cub/block/block_raking_layout.cuh
torch_dwconv/cub/block/block_reduce.cuh
torch_dwconv/cub/block/block_scan.cuh
torch_dwconv/cub/block/block_shuffle.cuh
torch_dwconv/cub/block/block_store.cuh
torch_dwconv/cub/block/specializations/block_histogram_atomic.cuh
torch_dwconv/cub/block/specializations/block_histogram_sort.cuh
torch_dwconv/cub/block/specializations/block_reduce_raking.cuh
torch_dwconv/cub/block/specializations/block_reduce_raking_commutative_only.cuh
