Metadata-Version: 1.2
Name: torch-dwconv
Version: 0.1.0
Summary: Faster depthwise convolutions for PyTorch
Home-page: https://github.com/rosinality/depthwise-conv-pytorch
Author: Kim Seonghyeon
Author-email: kim.seonghyeon@navercorp.com
License: MIT
Platform: UNKNOWN
Requires-Python: >=3.6
